datapackage_validate/__init__.py
datapackage_validate/compat.py
datapackage_validate/validation.py
datapackage_validate-0.0.1.dist-info/DESCRIPTION.rst
datapackage_validate-0.0.1.dist-info/METADATA
datapackage_validate-0.0.1.dist-info/metadata.json
datapackage_validate-0.0.1.dist-info/RECORD
datapackage_validate-0.0.1.dist-info/top_level.txt
datapackage_validate-0.0.1.dist-info/WHEEL
