Metadata-Version: 2.0
Name: datapackage-validate
Version: 0.0.1
Summary: A Python library to validate Data Package datapackage.json files.
Home-page: https://github.com/okfn/datapackage-validate-py
Author: Open Knowledge Foundation
Author-email: info@okfn.org
License: MIT
Platform: UNKNOWN
Classifier: Development Status :: 4 - Beta
Classifier: Intended Audience :: Developers
Classifier: License :: OSI Approved :: MIT License
Classifier: Operating System :: OS Independent
Classifier: Programming Language :: Python :: 2
Classifier: Programming Language :: Python :: 2.7
Classifier: Programming Language :: Python :: 3
Classifier: Programming Language :: Python :: 3.3
Classifier: Programming Language :: Python :: 3.4
Classifier: Topic :: Software Development :: Libraries :: Python Modules
Classifier: Topic :: Utilities
Requires-Dist: requests (>=2.8.0)
Requires-Dist: jsonschema (>=2.5.1)
Requires-Dist: datapackage-registry (>=0.0.2)
